<?xml version="1.0" encoding="UTF-8"?>
<con:testCase id="f9b0682c-5e17-48ed-9009-35237f0e3492" discardOkResults="false" failOnError="false" failTestCaseOnErrors="true" keepSession="false" name="TestCase1" searchProperties="true" timeout="0" xmlns:con="http://eviware.com/soapui/config">
  <con:settings>
    <con:setting id="f9b0682c-5e17-48ed-9009-35237f0e3492fileName">TestCase1</con:setting>
  </con:settings>
  <con:properties/>
  <con:reportParameters/>
  <con:environmentSpec>
    <con:entry environmentId="2408fd09-2032-4e1b-acdb-8c7777358df4">
      <con:authProfile>Inherit From Parent</con:authProfile>
    </con:entry>
  </con:environmentSpec>
</con:testCase>
